pottery/__init__.py
pottery/aionextid.py
pottery/aioredlock.py
pottery/annotations.py
pottery/base.py
pottery/bloom.py
pottery/cache.py
pottery/counter.py
pottery/deque.py
pottery/dict.py
pottery/exceptions.py
pottery/executor.py
pottery/hyper.py
pottery/list.py
pottery/monkey.py
pottery/nextid.py
pottery/py.typed
pottery/queue.py
pottery/redlock.py
pottery/set.py
pottery/timer.py
fsai_pottery-3.1.4.dist-info/LICENSE
fsai_pottery-3.1.4.dist-info/METADATA
fsai_pottery-3.1.4.dist-info/WHEEL
fsai_pottery-3.1.4.dist-info/RECORD
