Metadata-Version: 2.1
Name: fsai-pottery
Version: 3.1.4
Summary: Redis for humans. 🌎🌍🌏
License: Apache License
Author: Rajiv Bakulesh Shah
Requires-Python: >=3.7,<4
Classifier: License :: Other/Proprietary License
Classifier: Programming Language :: Python :: 3
Classifier: Programming Language :: Python :: 3.7
Classifier: Programming Language :: Python :: 3.8
Classifier: Programming Language :: Python :: 3.9
Classifier: Programming Language :: Python :: 3.10
Classifier: Programming Language :: Python :: 3.11
Requires-Dist: async-timeout (>=4.0.2,<5.0.0)
Requires-Dist: attrs (>=21.4.0,<22.0.0)
Requires-Dist: bandit (>=1.7.4,<2.0.0)
Requires-Dist: bleach (>=4.1.0,<5.0.0)
Requires-Dist: certifi (>=2021.10.8,<2022.0.0)
Requires-Dist: charset-normalizer (>=2.0.12,<3.0.0)
Requires-Dist: click (>=8.0.4,<9.0.0)
Requires-Dist: colorama (>=0.4.4,<0.5.0)
Requires-Dist: coverage (>=6.3.2,<7.0.0)
Requires-Dist: deprecated (>=1.2.13,<2.0.0)
Requires-Dist: docutils (>=0.18.1,<0.19.0)
Requires-Dist: dparse (>=0.5.1,<0.6.0)
Requires-Dist: flake8 (>=4.0.1,<5.0.0)
Requires-Dist: gitdb (>=4.0.9,<5.0.0)
Requires-Dist: gitpython (>=3.1.27,<4.0.0)
Requires-Dist: hiredis (>=2.0.0,<3.0.0)
Requires-Dist: idna (>=3.3,<4.0)
Requires-Dist: importlib-metadata (>=4.2.0,<5.0.0)
Requires-Dist: iniconfig (>=1.1.1,<2.0.0)
Requires-Dist: isort (>=5.10.1,<6.0.0)
Requires-Dist: keyring (>=23.5.0,<24.0.0)
Requires-Dist: mccabe (>=0.6.1,<0.7.0)
Requires-Dist: mmh3 (>=3.0.0,<4.0.0)
Requires-Dist: mypy (>=0.941,<0.942)
Requires-Dist: mypy-extensions (>=0.4.3,<0.5.0)
Requires-Dist: packaging (>=21.3,<22.0)
Requires-Dist: pbr (>=5.8.1,<6.0.0)
Requires-Dist: pkginfo (>=1.8.2,<2.0.0)
Requires-Dist: pluggy (>=1.0.0,<2.0.0)
Requires-Dist: py (>=1.11.0,<2.0.0)
Requires-Dist: pycodestyle (>=2.8.0,<3.0.0)
Requires-Dist: pyflakes (>=2.4.0,<3.0.0)
Requires-Dist: pygments (>=2.11.2,<3.0.0)
Requires-Dist: pyparsing (>=3.0.7,<4.0.0)
Requires-Dist: pytest (>=7.1.0,<8.0.0)
Requires-Dist: pytest-asyncio (>=0.18.2,<0.19.0)
Requires-Dist: pytest-cov (>=3.0.0,<4.0.0)
Requires-Dist: pyyaml (>=6.0,<7.0)
Requires-Dist: readme-renderer (>=34.0,<35.0)
Requires-Dist: redis (>=4.2.2,<5.0.0)
Requires-Dist: requests (>=2.27.1,<3.0.0)
Requires-Dist: requests-toolbelt (>=0.9.1,<0.10.0)
Requires-Dist: rfc3986 (>=2.0.0,<3.0.0)
Requires-Dist: safety (>=1.10.3,<2.0.0)
Requires-Dist: six (>=1.16.0,<2.0.0)
Requires-Dist: smmap (>=5.0.0,<6.0.0)
Requires-Dist: stevedore (>=3.5.0,<4.0.0)
Requires-Dist: toml (>=0.10.2,<0.11.0)
Requires-Dist: tomli (>=2.0.1,<3.0.0)
Requires-Dist: tqdm (>=4.63.0,<5.0.0)
Requires-Dist: twine (>=3.8.0,<4.0.0)
Requires-Dist: types-redis (>=4.1.17,<5.0.0)
Requires-Dist: typing-extensions (>=4.1.1,<5.0.0)
Requires-Dist: urllib3 (>=1.26.8,<2.0.0)
Requires-Dist: webencodings (>=0.5.1,<0.6.0)
Requires-Dist: wrapt (>=1.14.0,<2.0.0)
Requires-Dist: zipp (>=3.7.0,<4.0.0)
